UART/Lab_3/and3_gate.vhd
LIBRARY ieee;
USE ieee.std_logic_1164.ALL;

entity and3_gate is
	port(

			x_and : in std_logic;
			y_and : in std_logic;
            z_and : in std_logic;

			out_and : out std_logic

		);
end entity and3_gate;


architecture rtl of and3_gate is

	begin
	
		out_and <= x_and and y_and and z_and;
		
end architecture rtl;

UART/Lab_3/and3_gatetb.vhd
LIBRARY ieee;
USE ieee.std_logic_1164.ALL;

entity and3_gatetb is

end entity and3_gatetb;


architecture rtl of and3_gatetb is

	component and3_gate is

        port(

			x_and : in std_logic;
			y_and : in std_logic;
            z_and : in std_logic;

			out_and : out std_logic

		);

    end component and3_gate;
    
    signal x_and, y_and, z_and, out_and : std_logic;

    begin

        and3Gate: and3_gate port map(
            x_and => x_and,
            y_and => y_and,
            z_and => z_and,

            out_and => out_and
        );
	
        testbench: process

            begin

                x_and <= '0';
                y_and <= '0';
                z_and <= '0';
                wait for 20 ns;
                assert (  (z_and ='0') )
                report "Test combination failed for 000" severity error;

                x_and <= '1';
                y_and <= '0';
                z_and <= '0';
                wait for 20 ns;
                assert (  (z_and ='0') )
                report "Test combination failed for 001" severity error;

                x_and <= '0';
                y_and <= '1';
                z_and <= '0';
                wait for 20 ns;
                assert (  (z_and ='0') )
                report "Test combination failed for 010" severity error;

                x_and <= '1';
                y_and <= '1';
                z_and <= '0';
                wait for 20 ns;
                assert (  (z_and ='0') )
                report "Test combination failed for 011" severity error;

                x_and <= '0';
                y_and <= '0';
                z_and <= '1';
                wait for 20 ns;
                assert (  (z_and ='0') )
                report "Test combination failed for 100" severity error;

                x_and <= '1';
                y_and <= '0';
                z_and <= '1';
                wait for 20 ns;
                assert (  (z_and ='0') )
                report "Test combination failed for 101" severity error;

                x_and <= '0';
                y_and <= '1';
                z_and <= '1';
                wait for 20 ns;
                assert (  (z_and ='0') )
                report "Test combination failed for 110" severity error;

                x_and <= '1';
                y_and <= '1';
                z_and <= '1';
                wait for 20 ns;
                assert (  (z_and ='1') )
                report "Test combination failed for 111" severity error;

                wait;

                
        end process;
		
		
end architecture rtl;

UART/Lab_3/and3_gatetb.vcd
$date
  Sun Nov 06 09:35:27 2022
$end
$version
  GHDL v0
$end
$timescale
  1 fs
$end
$scope module standard $end
$upscope $end
$scope module std_logic_1164 $end
$upscope $end
$scope module and3_gatetb $end
$var reg 1 ! x_and $end
$var reg 1 " y_and $end
$var reg 1 # z_and $end
$var reg 1 $ out_and $end
$scope module and3gate $end
$var reg 1 % x_and $end
$var reg 1 & y_and $end
$var reg 1 ' z_and $end
$var reg 1 ( out_and $end
$upscope $end
$upscope $end
$enddefinitions $end
#0
0!
0"
0#
0$
0%
0&
0'
0(
#20000000
1!
1%
#40000000
0!
1"
0%
1&
#60000000
1!
1%
#80000000
0!
0"
1#
0%
0&
1'
#100000000
1!
1%
#120000000
0!
1"
0%
1&
#140000000
1!
1$
1%
1(
