UART/Lab_3/sr_ff.vhd
LIBRARY ieee;
USE ieee.std_logic_1164.ALL;

entity sr_ff is
	port(
	
		i_set, i_reset : in std_logic;
		i_enable : in std_logic;
		o_q, o_qBar : out std_logic
	
	);
end sr_ff;

architecture rtl of sr_ff is

	signal int_q, int_qBar : std_logic;
	signal int_sSignal, int_rSignal : std_logic;

	begin
	
		-- Concurrent Signal Assignment
		
		int_sSignal <= i_set nand i_enable;
		int_rSignal <= i_enable nand i_reset;
		int_q <= int_sSignal nand int_qBar;
		int_qBar <= int_q nand int_rSignal;
		
		-- Output Driver
		
		o_q <= int_q;
		o_qBar <= int_qBar;

end architecture rtl;

UART/Lab_3/d_ff.vhd
LIBRARY ieee;
USE ieee.std_logic_1164.ALL;

entity d_ff is
	port(
	
		i_d : in std_logic;
		i_clock : in std_logic;
		o_q, o_qBar : out std_logic

	);
end entity d_ff;

architecture rtl of d_ff is

	signal int_q, int_qBar : std_logic;
	signal int_d, int_dBar : std_logic;
	signal int_notD, int_notClock : std_logic;
	
	component sr_ff
		port(
			i_set, i_reset : in std_logic;
			i_enable : in std_logic;
			o_q, o_qBar : out std_logic
		);
	end component sr_ff;
	
	begin
	
		-- Component Instantiation
		
		first : sr_ff port map ( i_d, int_notD, int_notClock, int_q, int_qBar);
								  
		second : sr_ff port map ( int_q, int_qBar, i_clock, o_q, o_qBar);

		-- Concurrent Signal Assignment

		int_notD <= not(i_d);
		int_notClock <= not(i_clock);
		
end architecture rtl;

UART/Lab_3/d_fftb.vhd
LIBRARY ieee;
USE ieee.std_logic_1164.ALL;

entity d_fftb is
end entity d_fftb;

architecture rtl of d_fftb is

    component d_ff is

        port(
	
            i_d : in std_logic;
            i_clock : in std_logic;
            o_q, o_qBar : out std_logic

    	);
    
    end component d_ff;
    
    constant T : time := 20 ns;
    signal i_d, i_clock, o_q, o_qBar : std_logic := '0';

    begin

        flipFlop : d_ff port map (
            i_d => i_d,
            i_clock => i_clock,

            o_q => o_q,
            o_qBar => o_qBar
        );


        -- continuous clock
        process

            begin

                i_clock <= '0';
                wait for T/2;

                i_clock <= '1';
                wait for T/2;


        end process;

        testbench: process

            begin

                i_d <= '0';
                wait for 20 ns;
                assert( (o_q ='0') and (o_qBar ='1') )
                report "Test failed for D=0" severity error;

                i_d <= '1';
                wait for 20 ns;
                assert( (o_q ='1') and (o_qBar ='0') )
                report "Test failed for D=1" severity error;

        end process;
        

end rtl ; -- tFlipFloptb

UART/Lab_3/dFlipFlopTb.vcd
$date
  Sat Nov 05 11:18:33 2022
$end
$version
  GHDL v0
$end
$timescale
  1 fs
$end
$scope module standard $end
$upscope $end
$scope module std_logic_1164 $end
$upscope $end
$scope module d_fftb $end
$var reg 1 ! i_d $end
$var reg 1 " i_clock $end
$var reg 1 # o_q $end
$var reg 1 $ o_qbar $end
$scope module flipflop $end
$var reg 1 % i_d $end
$var reg 1 & i_clock $end
$var reg 1 ' o_q $end
$var reg 1 ( o_qbar $end
$var reg 1 ) int_q $end
$var reg 1 * int_qbar $end
$var reg 1 + int_d $end
$var reg 1 , int_dbar $end
$var reg 1 - int_notd $end
$var reg 1 . int_notclock $end
$scope module first $end
$var reg 1 / i_set $end
$var reg 1 0 i_reset $end
$var reg 1 1 i_enable $end
$var reg 1 2 o_q $end
$var reg 1 3 o_qbar $end
$var reg 1 4 int_q $end
$var reg 1 5 int_qbar $end
$var reg 1 6 int_ssignal $end
$var reg 1 7 int_rsignal $end
$upscope $end
$scope module second $end
$var reg 1 8 i_set $end
$var reg 1 9 i_reset $end
$var reg 1 : i_enable $end
$var reg 1 ; o_q $end
$var reg 1 < o_qbar $end
$var reg 1 = int_q $end
$var reg 1 > int_qbar $end
$var reg 1 ? int_ssignal $end
$var reg 1 @ int_rsignal $end
$upscope $end
$upscope $end
$upscope $end
$enddefinitions $end
#0
0!
0"
U#
U$
0%
0&
U'
U(
0)
1*
U+
U,
1-
1.
0/
10
11
02
13
04
15
16
07
08
19
0:
U;
U<
U=
U>
1?
1@
#10000000
1"
0#
1$
1&
0'
1(
0.
01
17
1:
0;
1<
0=
1>
0@
#20000000
1!
0"
1%
0&
1)
0*
0-
1.
1/
00
11
12
03
14
05
06
18
09
0:
1@
#30000000
1"
1#
0$
1&
1'
0(
0.
01
16
1:
1;
0<
1=
0>
0?
#40000000
0!
0"
0%
0&
0)
1*
1-
1.
0/
10
11
02
13
04
15
07
08
19
0:
1?
#50000000
1"
0#
1$
1&
0'
1(
0.
01
17
1:
0;
1<
0=
1>
0@
#60000000
1!
0"
1%
0&
1)
0*
0-
1.
1/
00
11
12
03
14
05
06
18
09
0:
1@
#70000000
1"
1#
0$
1&
1'
0(
0.
01
16
1:
1;
0<
1=
0>
0?
#80000000
0!
0"
0%
0&
0)
1*
1-
1.
0/
10
11
02
13
04
15
07
08
19
0:
1?
#90000000
1"
0#
1$
1&
0'
1(
0.
01
17
1:
0;
1<
0=
1>
0@
#100000000
1!
0"
1%
0&
1)
0*
0-
1.
1/
00
11
12
03
14
05
06
18
09
0:
1@
#110000000
1"
1#
0$
1&
1'
0(
0.
01
16
1:
1;
0<
1=
0>
0?
#120000000
0!
0"
0%
0&
0)
1*
1-
1.
0/
10
11
02
13
04
15
07
08
19
0:
1?
#130000000
1"
0#
1$
1&
0'
1(
0.
01
17
1:
0;
1<
0=
1>
0@
#140000000
1!
0"
1%
0&
1)
0*
0-
1.
1/
00
11
12
03
14
05
06
18
09
0:
1@
#150000000
1"
1#
0$
1&
1'
0(
0.
01
16
1:
1;
0<
1=
0>
0?
#160000000
0!
0"
0%
0&
0)
1*
1-
1.
0/
10
11
02
13
04
15
07
08
19
0:
1?
#170000000
1"
0#
1$
1&
0'
1(
0.
01
17
1:
0;
1<
0=
1>
0@
#180000000
1!
0"
1%
0&
1)
0*
0-
1.
1/
00
11
12
03
14
05
06
18
09
0:
1@
#190000000
1"
1#
0$
1&
1'
0(
0.
01
16
1:
1;
0<
1=
0>
0?
#200000000
0!
0"
0%
0&
0)
1*
1-
1.
0/
10
11
02
13
04
15
07
08
19
0:
1?
#210000000
1"
0#
1$
1&
0'
1(
0.
01
17
1:
0;
1<
0=
1>
0@
#220000000
1!
0"
1%
0&
1)
0*
0-
1.
1/
00
11
12
03
14
05
06
18
09
0:
1@
#230000000
1"
1#
0$
1&
1'
0(
0.
01
16
1:
1;
0<
1=
0>
0?
#240000000
0!
0"
0%
0&
0)
1*
1-
1.
0/
10
11
02
13
04
15
07
08
19
0:
1?
#250000000
1"
0#
1$
1&
0'
1(
0.
01
17
1:
0;
1<
0=
1>
0@
#260000000
1!
0"
1%
0&
1)
0*
0-
1.
1/
00
11
12
03
14
05
06
18
09
0:
1@
#270000000
1"
1#
0$
1&
1'
0(
0.
01
16
1:
1;
0<
1=
0>
0?
#280000000
0!
0"
0%
0&
0)
1*
1-
1.
0/
10
11
02
13
04
15
07
08
19
0:
1?
#290000000
1"
0#
1$
1&
0'
1(
0.
01
17
1:
0;
1<
0=
1>
0@
#300000000
1!
0"
1%
0&
1)
0*
0-
1.
1/
00
11
12
03
14
05
06
18
09
0:
1@
#310000000
1"
1#
0$
1&
1'
0(
0.
01
16
1:
1;
0<
1=
0>
0?
#320000000
0!
0"
0%
0&
0)
1*
1-
1.
0/
10
11
02
13
04
15
07
08
19
0:
1?
#330000000
1"
0#
1$
1&
0'
1(
0.
01
17
1:
0;
1<
0=
1>
0@
#340000000
1!
0"
1%
0&
1)
0*
0-
1.
1/
00
11
12
03
14
05
06
18
09
0:
1@
#350000000
1"
1#
0$
1&
1'
0(
0.
01
16
1:
1;
0<
1=
0>
0?
#360000000
0!
0"
0%
0&
0)
1*
1-
1.
0/
10
11
02
13
04
15
07
08
19
0:
1?
#370000000
1"
0#
1$
1&
0'
1(
0.
01
17
1:
0;
1<
0=
1>
0@
#380000000
1!
0"
1%
0&
1)
0*
0-
1.
1/
00
11
12
03
14
05
06
18
09
0:
1@
#390000000
1"
1#
0$
1&
1'
0(
0.
01
16
1:
1;
0<
1=
0>
0?
#400000000
0!
0"
0%
0&
0)
1*
1-
1.
0/
10
11
02
13
04
15
07
08
19
0:
1?
