UART/Lab_3/sr_ff.vhd
LIBRARY ieee;
USE ieee.std_logic_1164.ALL;

entity sr_ff is
	port(
	
		i_set, i_reset : in std_logic;
		i_enable : in std_logic;
		o_q, o_qBar : out std_logic
	
	);
end sr_ff;

architecture rtl of sr_ff is

	signal int_q, int_qBar : std_logic;
	signal int_sSignal, int_rSignal : std_logic;

	begin
	
		-- Concurrent Signal Assignment
		
		int_sSignal <= i_set nand i_enable;
		int_rSignal <= i_enable nand i_reset;
		int_q <= int_sSignal nand int_qBar;
		int_qBar <= int_q nand int_rSignal;
		
		-- Output Driver
		
		o_q <= int_q;
		o_qBar <= int_qBar;

end architecture rtl;

UART/Lab_3/d_ff.vhd
LIBRARY ieee;
USE ieee.std_logic_1164.ALL;

entity d_ff is
	port(
	
		i_d : in std_logic;
		i_clock : in std_logic;
		o_q, o_qBar : out std_logic

	);
end entity d_ff;

architecture rtl of d_ff is

	signal int_q, int_qBar : std_logic;
	signal int_d, int_dBar : std_logic;
	signal int_notD, int_notClock : std_logic;
	
	component sr_ff
		port(
			i_set, i_reset : in std_logic;
			i_enable : in std_logic;
			o_q, o_qBar : out std_logic
		);
	end component sr_ff;
	
	begin
	
		-- Component Instantiation
		
		first : sr_ff port map ( i_d, int_notD, int_notClock, int_q, int_qBar);
								  
		second : sr_ff port map ( int_q, int_qBar, i_clock, o_q, o_qBar);

		-- Concurrent Signal Assignment

		int_notD <= not(i_d);
		int_notClock <= not(i_clock);
		
end architecture rtl;

UART/Lab_3/or_gate.vhd
LIBRARY ieee;
USE ieee.std_logic_1164.ALL;

entity or_gate is
	port(

			x_or : in std_logic;
			y_or : in std_logic;

			z_or : out std_logic

		);
end entity or_gate;


architecture rtl of or_gate is

	begin
	
		z_or <= x_or or y_or;
		
end architecture rtl;

UART/Lab_3/and_gate.vhd
LIBRARY ieee;
USE ieee.std_logic_1164.ALL;

entity and_gate is
	port(

			x_and : in std_logic;
			y_and : in std_logic;

			z_and : out std_logic

		);
end entity and_gate;


architecture rtl of and_gate is

	begin
	
		z_and <= x_and and y_and;
		
end architecture rtl;

UART/Lab_3/enabledDFF.vhd
LIBRARY ieee;
USE ieee.std_logic_1164.ALL;

entity enabledDFF is
	port(
	
		d : in std_logic;
		d_clock : in std_logic;
		en_d : in std_logic;
		
		outQ, outQBar : out std_logic

	);
end entity enabledDFF;

architecture rtl of enabledDFF is

	signal AND1toOR, AND2toOR, ORtoDFF, Q, not_en : std_logic;
	
	component or_gate
		port(

			x_or : in std_logic;
			y_or : in std_logic;

			z_or : out std_logic

		);
	end component or_gate;

	component and_gate
		port(

			x_and : in std_logic;
			y_and : in std_logic;

			z_and : out std_logic

		);
	end component and_gate;
	
	component d_ff
		port(

			i_d : in std_logic;
			i_clock : in std_logic;
			o_q, o_qBar : out std_logic

		);
	end component d_ff;
	
	
	begin

		not_en <= not en_d ;
	
		and1 : and_gate port map (d, en_d, AND1toOR);
					
		and2 : and_gate port map (Q, not_en, AND2toOR);
					
		or1 : or_gate port map (AND1toOR, AND2toOR, ORtoDFF);
					
		dflipflop : d_ff port map (ORtoDFF, d_clock, Q, outQBar);
	
		outQ <= Q;
		
end architecture rtl;

UART/Lab_3/down_counter_4bits.vhd
LIBRARY ieee;
USE ieee.std_logic_1164.ALL;

entity down_counter_4bits is
	port(
	
		inputSignal : in std_logic_vector(3 downto 0);
		enable : in std_logic;
		clock : in std_logic;
		resetBar : in std_logic;
		
		finish : out std_logic
	);
end entity down_counter_4bits;

architecture rtl of down_counter_4bits is

	signal Dff3, Dff2, Dff1, Dff0, y3, y2, y1, y0, Din3, Din2, Din1, Din0 : std_logic;
	
	component enabledDFF is
		port(
	
			d : in std_logic;
			d_clock : in std_logic;
			en_d : in std_logic;
			
			outQ, outQBar : out std_logic

		);
	end component enabledDFF;
	
	
	begin
		
		Dff3 <= y3 and (y2 or y1 or y0);
		Dff2 <= (y2 and (y0 or y1)) or (not(y0) and not(y1) and not(y2));
		Dff1 <= y0 xor not(y1);
		Dff0 <= not(y0);
		
		Din0 <= (Dff0 and inputSignal(0)) or (not(resetBar) and inputSignal(0)) or (Dff0 and resetBar);
		Din1 <= (Dff1 and inputSignal(1)) or (not(resetBar) and inputSignal(1)) or (Dff1 and resetBar);
		Din2 <= (Dff2 and inputSignal(2)) or (not(resetBar) and inputSignal(2)) or (Dff2 and resetBar);
		Din3 <= (Dff3 and inputSignal(3)) or (not(resetBar) and inputSignal(3)) or (Dff3 and resetBar);
		
		d0 : enabledDFF port map(Din0, clock, enable, y0);
				
		d1 : enabledDFF port map(Din1, clock, enable, y1);
				
		d2 : enabledDFF port map(Din2, clock, enable, y2);
				
		d3 : enabledDFF port map(Din3, clock, enable, y3);
		
		finish <= not(y0) and not(y1) and not(y2) and not(y3);
		
	
end architecture rtl;

UART/Lab_3/down_counter_4bitstb.vhd
library ieee;
use ieee.std_logic_1164.all;

entity down_counter_4bitstb is
end down_counter_4bitstb;

architecture rtl of down_counter_4bitstb is

    component down_counter_4bits is 

        port (
            inputSignal : in std_logic_vector(3 downto 0);
            enable : in std_logic;
            clock : in std_logic;
            resetBar : in std_logic;
            
            finish : out std_logic
        );

    end component down_counter_4bits;

    signal inSignal : std_logic_vector(3 downto 0);
    constant T : time := 20 ns;
    signal enable, clock, resetBar, finish : std_logic;

    begin

        downCounter4BitsComponent : down_counter_4bits port map(

            inputSignal => inSignal,
            enable => enable,
            clock => clock,
            resetBar => resetBar,
            finish => finish

        );

        clockPrcess : process

            begin

                clock <= '1';
                wait for T/2;

                clock <= '0';
                wait for T/2;


        end process;


        testbenchDownCounter4Bits: process

                begin 

                    inSignal <= "1111";
                    enable <= '1';
                    resetBar <= '0', '1' after 40 ns;

                    assert(finish ='1')
                    report "Test failed for input signal = 1111" severity error;

                    wait;
                

        end process;

end rtl ; -- rtl

UART/Lab_3/down_counter_4bits.vcd
$date
  Wed Nov 09 20:46:47 2022
$end
$version
  GHDL v0
$end
$timescale
  1 fs
$end
$scope module standard $end
$upscope $end
$scope module std_logic_1164 $end
$upscope $end
$scope module down_counter_4bitstb $end
$var reg 4 ! insignal[3:0] $end
$var reg 1 " enable $end
$var reg 1 # clock $end
$var reg 1 $ resetbar $end
$var reg 1 % finish $end
$scope module downcounter4bitscomponent $end
$var reg 4 & inputsignal[3:0] $end
$var reg 1 ' enable $end
$var reg 1 ( clock $end
$var reg 1 ) resetbar $end
$var reg 1 * finish $end
$var reg 1 + dff3 $end
$var reg 1 , dff2 $end
$var reg 1 - dff1 $end
$var reg 1 . dff0 $end
$var reg 1 / y3 $end
$var reg 1 0 y2 $end
$var reg 1 1 y1 $end
$var reg 1 2 y0 $end
$var reg 1 3 din3 $end
$var reg 1 4 din2 $end
$var reg 1 5 din1 $end
$var reg 1 6 din0 $end
$scope module d0 $end
$var reg 1 7 d $end
$var reg 1 8 d_clock $end
$var reg 1 9 en_d $end
$var reg 1 : outq $end
$var reg 1 ; outqbar $end
$var reg 1 < and1toor $end
$var reg 1 = and2toor $end
$var reg 1 > ortodff $end
$var reg 1 ? q $end
$var reg 1 @ not_en $end
$scope module and1 $end
$upscope $end
$scope module and2 $end
$upscope $end
$scope module or1 $end
$upscope $end
$scope module dflipflop $end
$var reg 1 A i_d $end
$var reg 1 B i_clock $end
$var reg 1 C o_q $end
$var reg 1 D o_qbar $end
$var reg 1 E int_q $end
$var reg 1 F int_qbar $end
$var reg 1 G int_d $end
$var reg 1 H int_dbar $end
$var reg 1 I int_notd $end
$var reg 1 J int_notclock $end
$scope module first $end
$var reg 1 K i_set $end
$var reg 1 L i_reset $end
$var reg 1 M i_enable $end
$var reg 1 N o_q $end
$var reg 1 O o_qbar $end
$var reg 1 P int_q $end
$var reg 1 Q int_qbar $end
$var reg 1 R int_ssignal $end
$var reg 1 S int_rsignal $end
$upscope $end
$scope module second $end
$var reg 1 T i_set $end
$var reg 1 U i_reset $end
$var reg 1 V i_enable $end
$var reg 1 W o_q $end
$var reg 1 X o_qbar $end
$var reg 1 Y int_q $end
$var reg 1 Z int_qbar $end
$var reg 1 [ int_ssignal $end
$var reg 1 \ int_rsignal $end
$upscope $end
$upscope $end
$upscope $end
$scope module d1 $end
$var reg 1 ] d $end
$var reg 1 ^ d_clock $end
$var reg 1 _ en_d $end
$var reg 1 ` outq $end
$var reg 1 a outqbar $end
$var reg 1 b and1toor $end
$var reg 1 c and2toor $end
$var reg 1 d ortodff $end
$var reg 1 e q $end
$var reg 1 f not_en $end
$scope module and1 $end
$upscope $end
$scope module and2 $end
$upscope $end
$scope module or1 $end
$upscope $end
$scope module dflipflop $end
$var reg 1 g i_d $end
$var reg 1 h i_clock $end
$var reg 1 i o_q $end
$var reg 1 j o_qbar $end
$var reg 1 k int_q $end
$var reg 1 l int_qbar $end
$var reg 1 m int_d $end
$var reg 1 n int_dbar $end
$var reg 1 o int_notd $end
$var reg 1 p int_notclock $end
$scope module first $end
$var reg 1 q i_set $end
$var reg 1 r i_reset $end
$var reg 1 s i_enable $end
$var reg 1 t o_q $end
$var reg 1 u o_qbar $end
$var reg 1 v int_q $end
$var reg 1 w int_qbar $end
$var reg 1 x int_ssignal $end
$var reg 1 y int_rsignal $end
$upscope $end
$scope module second $end
$var reg 1 z i_set $end
$var reg 1 { i_reset $end
$var reg 1 | i_enable $end
$var reg 1 } o_q $end
$var reg 1 !" o_qbar $end
$var reg 1 "" int_q $end
$var reg 1 #" int_qbar $end
$var reg 1 $" int_ssignal $end
$var reg 1 %" int_rsignal $end
$upscope $end
$upscope $end
$upscope $end
$scope module d2 $end
$var reg 1 &" d $end
$var reg 1 '" d_clock $end
$var reg 1 (" en_d $end
$var reg 1 )" outq $end
$var reg 1 *" outqbar $end
$var reg 1 +" and1toor $end
$var reg 1 ," and2toor $end
$var reg 1 -" ortodff $end
$var reg 1 ." q $end
$var reg 1 /" not_en $end
$scope module and1 $end
$upscope $end
$scope module and2 $end
$upscope $end
$scope module or1 $end
$upscope $end
$scope module dflipflop $end
$var reg 1 0" i_d $end
$var reg 1 1" i_clock $end
$var reg 1 2" o_q $end
$var reg 1 3" o_qbar $end
$var reg 1 4" int_q $end
$var reg 1 5" int_qbar $end
$var reg 1 6" int_d $end
$var reg 1 7" int_dbar $end
$var reg 1 8" int_notd $end
$var reg 1 9" int_notclock $end
$scope module first $end
$var reg 1 :" i_set $end
$var reg 1 ;" i_reset $end
$var reg 1 <" i_enable $end
$var reg 1 =" o_q $end
$var reg 1 >" o_qbar $end
$var reg 1 ?" int_q $end
$var reg 1 @" int_qbar $end
$var reg 1 A" int_ssignal $end
$var reg 1 B" int_rsignal $end
$upscope $end
$scope module second $end
$var reg 1 C" i_set $end
$var reg 1 D" i_reset $end
$var reg 1 E" i_enable $end
$var reg 1 F" o_q $end
$var reg 1 G" o_qbar $end
$var reg 1 H" int_q $end
$var reg 1 I" int_qbar $end
$var reg 1 J" int_ssignal $end
$var reg 1 K" int_rsignal $end
$upscope $end
$upscope $end
$upscope $end
$scope module d3 $end
$var reg 1 L" d $end
$var reg 1 M" d_clock $end
$var reg 1 N" en_d $end
$var reg 1 O" outq $end
$var reg 1 P" outqbar $end
$var reg 1 Q" and1toor $end
$var reg 1 R" and2toor $end
$var reg 1 S" ortodff $end
$var reg 1 T" q $end
$var reg 1 U" not_en $end
$scope module and1 $end
$upscope $end
$scope module and2 $end
$upscope $end
$scope module or1 $end
$upscope $end
$scope module dflipflop $end
$var reg 1 V" i_d $end
$var reg 1 W" i_clock $end
$var reg 1 X" o_q $end
$var reg 1 Y" o_qbar $end
$var reg 1 Z" int_q $end
$var reg 1 [" int_qbar $end
$var reg 1 \" int_d $end
$var reg 1 ]" int_dbar $end
$var reg 1 ^" int_notd $end
$var reg 1 _" int_notclock $end
$scope module first $end
$var reg 1 `" i_set $end
$var reg 1 a" i_reset $end
$var reg 1 b" i_enable $end
$var reg 1 c" o_q $end
$var reg 1 d" o_qbar $end
$var reg 1 e" int_q $end
$var reg 1 f" int_qbar $end
$var reg 1 g" int_ssignal $end
$var reg 1 h" int_rsignal $end
$upscope $end
$scope module second $end
$var reg 1 i" i_set $end
$var reg 1 j" i_reset $end
$var reg 1 k" i_enable $end
$var reg 1 l" o_q $end
$var reg 1 m" o_qbar $end
$var reg 1 n" int_q $end
$var reg 1 o" int_qbar $end
$var reg 1 p" int_ssignal $end
$var reg 1 q" int_rsignal $end
$upscope $end
$upscope $end
$upscope $end
$upscope $end
$upscope $end
$enddefinitions $end
#0
b1111 !
1"
1#
0$
U%
b1111 &
1'
1(
0)
U*
U+
U,
U-
U.
U/
U0
U1
U2
13
14
15
16
17
18
19
U:
U;
U<
U=
U>
U?
0@
UA
1B
UC
UD
UE
UF
UG
UH
UI
0J
UK
UL
0M
UN
UO
UP
UQ
1R
1S
UT
UU
1V
UW
UX
UY
UZ
U[
U\
1]
1^
1_
U`
Ua
Ub
Uc
Ud
Ue
0f
Ug
1h
Ui
Uj
Uk
Ul
Um
Un
Uo
0p
Uq
Ur
0s
Ut
Uu
Uv
Uw
1x
1y
Uz
U{
1|
U}
U!"
U""
U#"
U$"
U%"
1&"
1'"
1("
U)"
U*"
U+"
U,"
U-"
U."
0/"
U0"
11"
U2"
U3"
U4"
U5"
U6"
U7"
U8"
09"
U:"
U;"
0<"
U="
U>"
U?"
U@"
1A"
1B"
UC"
UD"
1E"
UF"
UG"
UH"
UI"
UJ"
UK"
1L"
1M"
1N"
UO"
UP"
UQ"
UR"
US"
UT"
0U"
UV"
1W"
UX"
UY"
UZ"
U["
U\"
U]"
U^"
0_"
U`"
Ua"
0b"
Uc"
Ud"
Ue"
Uf"
1g"
1h"
Ui"
Uj"
1k"
Ul"
Um"
Un"
Uo"
Up"
Uq"
#10000000
0#
0(
08
0B
1J
1M
UR
US
0V
1[
1\
0^
0h
1p
1s
Ux
Uy
0|
1$"
1%"
0'"
01"
19"
1<"
UA"
UB"
0E"
1J"
1K"
0M"
0W"
1_"
1b"
Ug"
Uh"
0k"
1p"
1q"
#20000000
1#
1(
18
1B
0J
0M
1R
1S
1V
U[
U\
1^
1h
0p
0s
1x
1y
1|
U$"
U%"
1'"
11"
09"
0<"
1A"
1B"
1E"
UJ"
UK"
1M"
1W"
0_"
0b"
1g"
1h"
1k"
Up"
Uq"
#30000000
0#
0(
08
0B
1J
1M
UR
US
0V
1[
1\
0^
0h
1p
1s
Ux
Uy
0|
1$"
1%"
0'"
01"
19"
1<"
UA"
UB"
0E"
1J"
1K"
0M"
0W"
1_"
1b"
Ug"
Uh"
0k"
1p"
1q"
#40000000
1#
1$
1(
1)
U3
U4
U5
U6
U7
18
1B
0J
0M
1R
1S
1V
U[
U\
U]
1^
1h
0p
0s
1x
1y
1|
U$"
U%"
U&"
1'"
11"
09"
0<"
1A"
1B"
1E"
UJ"
UK"
UL"
1M"
1W"
0_"
0b"
1g"
1h"
1k"
Up"
Uq"
#50000000
0#
0(
08
0B
1J
1M
UR
US
0V
1[
1\
0^
0h
1p
1s
Ux
Uy
0|
1$"
1%"
0'"
01"
19"
1<"
UA"
UB"
0E"
1J"
1K"
0M"
0W"
1_"
1b"
Ug"
Uh"
0k"
1p"
1q"
#60000000
1#
1(
18
1B
0J
0M
1R
1S
1V
U[
U\
1^
1h
0p
0s
1x
1y
1|
U$"
U%"
1'"
11"
09"
0<"
1A"
1B"
1E"
UJ"
UK"
1M"
1W"
0_"
0b"
1g"
1h"
1k"
Up"
Uq"
#70000000
0#
0(
08
0B
1J
1M
UR
US
0V
1[
1\
0^
0h
1p
1s
Ux
Uy
0|
1$"
1%"
0'"
01"
19"
1<"
UA"
UB"
0E"
1J"
1K"
0M"
0W"
1_"
1b"
Ug"
Uh"
0k"
1p"
1q"
#80000000
1#
1(
18
1B
0J
0M
1R
1S
1V
U[
U\
1^
1h
0p
0s
1x
1y
1|
U$"
U%"
1'"
11"
09"
0<"
1A"
1B"
1E"
UJ"
UK"
1M"
1W"
0_"
0b"
1g"
1h"
1k"
Up"
Uq"
#90000000
0#
0(
08
0B
1J
1M
UR
US
0V
1[
1\
0^
0h
1p
1s
Ux
Uy
0|
1$"
1%"
0'"
01"
19"
1<"
UA"
UB"
0E"
1J"
1K"
0M"
0W"
1_"
1b"
Ug"
Uh"
0k"
1p"
1q"
#100000000
1#
1(
18
1B
0J
0M
1R
1S
1V
U[
U\
1^
1h
0p
0s
1x
1y
1|
U$"
U%"
1'"
11"
09"
0<"
1A"
1B"
1E"
UJ"
UK"
1M"
1W"
0_"
0b"
1g"
1h"
1k"
Up"
Uq"
#110000000
0#
0(
08
0B
1J
1M
UR
US
0V
1[
1\
0^
0h
1p
1s
Ux
Uy
0|
1$"
1%"
0'"
01"
19"
1<"
UA"
UB"
0E"
1J"
1K"
0M"
0W"
1_"
1b"
Ug"
Uh"
0k"
1p"
1q"
#120000000
1#
1(
18
1B
0J
0M
1R
1S
1V
U[
U\
1^
1h
0p
0s
1x
1y
1|
U$"
U%"
1'"
11"
09"
0<"
1A"
1B"
1E"
UJ"
UK"
1M"
1W"
0_"
0b"
1g"
1h"
1k"
Up"
Uq"
#130000000
0#
0(
08
0B
1J
1M
UR
US
0V
1[
1\
0^
0h
1p
1s
Ux
Uy
0|
1$"
1%"
0'"
01"
19"
1<"
UA"
UB"
0E"
1J"
1K"
0M"
0W"
1_"
1b"
Ug"
Uh"
0k"
1p"
1q"
#140000000
1#
1(
18
1B
0J
0M
1R
1S
1V
U[
U\
1^
1h
0p
0s
1x
1y
1|
U$"
U%"
1'"
11"
09"
0<"
1A"
1B"
1E"
UJ"
UK"
1M"
1W"
0_"
0b"
1g"
1h"
1k"
Up"
Uq"
#150000000
0#
0(
08
0B
1J
1M
UR
US
0V
1[
1\
0^
0h
1p
1s
Ux
Uy
0|
1$"
1%"
0'"
01"
19"
1<"
UA"
UB"
0E"
1J"
1K"
0M"
0W"
1_"
1b"
Ug"
Uh"
0k"
1p"
1q"
#160000000
1#
1(
18
1B
0J
0M
1R
1S
1V
U[
U\
1^
1h
0p
0s
1x
1y
1|
U$"
U%"
1'"
11"
09"
0<"
1A"
1B"
1E"
UJ"
UK"
1M"
1W"
0_"
0b"
1g"
1h"
1k"
Up"
Uq"
#170000000
0#
0(
08
0B
1J
1M
UR
US
0V
1[
1\
0^
0h
1p
1s
Ux
Uy
0|
1$"
1%"
0'"
01"
19"
1<"
UA"
UB"
0E"
1J"
1K"
0M"
0W"
1_"
1b"
Ug"
Uh"
0k"
1p"
1q"
#180000000
1#
1(
18
1B
0J
0M
1R
1S
1V
U[
U\
1^
1h
0p
0s
1x
1y
1|
U$"
U%"
1'"
11"
09"
0<"
1A"
1B"
1E"
UJ"
UK"
1M"
1W"
0_"
0b"
1g"
1h"
1k"
Up"
Uq"
#190000000
0#
0(
08
0B
1J
1M
UR
US
0V
1[
1\
0^
0h
1p
1s
Ux
Uy
0|
1$"
1%"
0'"
01"
19"
1<"
UA"
UB"
0E"
1J"
1K"
0M"
0W"
1_"
1b"
Ug"
Uh"
0k"
1p"
1q"
#200000000
1#
1(
18
1B
0J
0M
1R
1S
1V
U[
U\
1^
1h
0p
0s
1x
1y
1|
U$"
U%"
1'"
11"
09"
0<"
1A"
1B"
1E"
UJ"
UK"
1M"
1W"
0_"
0b"
1g"
1h"
1k"
Up"
Uq"
#210000000
0#
0(
08
0B
1J
1M
UR
US
0V
1[
1\
0^
0h
1p
1s
Ux
Uy
0|
1$"
1%"
0'"
01"
19"
1<"
UA"
UB"
0E"
1J"
1K"
0M"
0W"
1_"
1b"
Ug"
Uh"
0k"
1p"
1q"
#220000000
1#
1(
18
1B
0J
0M
1R
1S
1V
U[
U\
1^
1h
0p
0s
1x
1y
1|
U$"
U%"
1'"
11"
09"
0<"
1A"
1B"
1E"
UJ"
UK"
1M"
1W"
0_"
0b"
1g"
1h"
1k"
Up"
Uq"
#230000000
0#
0(
08
0B
1J
1M
UR
US
0V
1[
1\
0^
0h
1p
1s
Ux
Uy
0|
1$"
1%"
0'"
01"
19"
1<"
UA"
UB"
0E"
1J"
1K"
0M"
0W"
1_"
1b"
Ug"
Uh"
0k"
1p"
1q"
#240000000
1#
1(
18
1B
0J
0M
1R
1S
1V
U[
U\
1^
1h
0p
0s
1x
1y
1|
U$"
U%"
1'"
11"
09"
0<"
1A"
1B"
1E"
UJ"
UK"
1M"
1W"
0_"
0b"
1g"
1h"
1k"
Up"
Uq"
#250000000
0#
0(
08
0B
1J
1M
UR
US
0V
1[
1\
0^
0h
1p
1s
Ux
Uy
0|
1$"
1%"
0'"
01"
19"
1<"
UA"
UB"
0E"
1J"
1K"
0M"
0W"
1_"
1b"
Ug"
Uh"
0k"
1p"
1q"
#260000000
1#
1(
18
1B
0J
0M
1R
1S
1V
U[
U\
1^
1h
0p
0s
1x
1y
1|
U$"
U%"
1'"
11"
09"
0<"
1A"
1B"
1E"
UJ"
UK"
1M"
1W"
0_"
0b"
1g"
1h"
1k"
Up"
Uq"
#270000000
0#
0(
08
0B
1J
1M
UR
US
0V
1[
1\
0^
0h
1p
1s
Ux
Uy
0|
1$"
1%"
0'"
01"
19"
1<"
UA"
UB"
0E"
1J"
1K"
0M"
0W"
1_"
1b"
Ug"
Uh"
0k"
1p"
1q"
#280000000
1#
1(
18
1B
0J
0M
1R
1S
1V
U[
U\
1^
1h
0p
0s
1x
1y
1|
U$"
U%"
1'"
11"
09"
0<"
1A"
1B"
1E"
UJ"
UK"
1M"
1W"
0_"
0b"
1g"
1h"
1k"
Up"
Uq"
#290000000
0#
0(
08
0B
1J
1M
UR
US
0V
1[
1\
0^
0h
1p
1s
Ux
Uy
0|
1$"
1%"
0'"
01"
19"
1<"
UA"
UB"
0E"
1J"
1K"
0M"
0W"
1_"
1b"
Ug"
Uh"
0k"
1p"
1q"
#300000000
1#
1(
18
1B
0J
0M
1R
1S
1V
U[
U\
1^
1h
0p
0s
1x
1y
1|
U$"
U%"
1'"
11"
09"
0<"
1A"
1B"
1E"
UJ"
UK"
1M"
1W"
0_"
0b"
1g"
1h"
1k"
Up"
Uq"
#310000000
0#
0(
08
0B
1J
1M
UR
US
0V
1[
1\
0^
0h
1p
1s
Ux
Uy
0|
1$"
1%"
0'"
01"
19"
1<"
UA"
UB"
0E"
1J"
1K"
0M"
0W"
1_"
1b"
Ug"
Uh"
0k"
1p"
1q"
#320000000
1#
1(
18
1B
0J
0M
1R
1S
1V
U[
U\
1^
1h
0p
0s
1x
1y
1|
U$"
U%"
1'"
11"
09"
0<"
1A"
1B"
1E"
UJ"
UK"
1M"
1W"
0_"
0b"
1g"
1h"
1k"
Up"
Uq"
#330000000
0#
0(
08
0B
1J
1M
UR
US
0V
1[
1\
0^
0h
1p
1s
Ux
Uy
0|
1$"
1%"
0'"
01"
19"
1<"
UA"
UB"
0E"
1J"
1K"
0M"
0W"
1_"
1b"
Ug"
Uh"
0k"
1p"
1q"
#340000000
1#
1(
18
1B
0J
0M
1R
1S
1V
U[
U\
1^
1h
0p
0s
1x
1y
1|
U$"
U%"
1'"
11"
09"
0<"
1A"
1B"
1E"
UJ"
UK"
1M"
1W"
0_"
0b"
1g"
1h"
1k"
Up"
Uq"
#350000000
0#
0(
08
0B
1J
1M
UR
US
0V
1[
1\
0^
0h
1p
1s
Ux
Uy
0|
1$"
1%"
0'"
01"
19"
1<"
UA"
UB"
0E"
1J"
1K"
0M"
0W"
1_"
1b"
Ug"
Uh"
0k"
1p"
1q"
#360000000
1#
1(
18
1B
0J
0M
1R
1S
1V
U[
U\
1^
1h
0p
0s
1x
1y
1|
U$"
U%"
1'"
11"
09"
0<"
1A"
1B"
1E"
UJ"
UK"
1M"
1W"
0_"
0b"
1g"
1h"
1k"
Up"
Uq"
#370000000
0#
0(
08
0B
1J
1M
UR
US
0V
1[
1\
0^
0h
1p
1s
Ux
Uy
0|
1$"
1%"
0'"
01"
19"
1<"
UA"
UB"
0E"
1J"
1K"
0M"
0W"
1_"
1b"
Ug"
Uh"
0k"
1p"
1q"
#380000000
1#
1(
18
1B
0J
0M
1R
1S
1V
U[
U\
1^
1h
0p
0s
1x
1y
1|
U$"
U%"
1'"
11"
09"
0<"
1A"
1B"
1E"
UJ"
UK"
1M"
1W"
0_"
0b"
1g"
1h"
1k"
Up"
Uq"
#390000000
0#
0(
08
0B
1J
1M
UR
US
0V
1[
1\
0^
0h
1p
1s
Ux
Uy
0|
1$"
1%"
0'"
01"
19"
1<"
UA"
UB"
0E"
1J"
1K"
0M"
0W"
1_"
1b"
Ug"
Uh"
0k"
1p"
1q"
#400000000
1#
1(
18
1B
0J
0M
1R
1S
1V
U[
U\
1^
1h
0p
0s
1x
1y
1|
U$"
U%"
1'"
11"
09"
0<"
1A"
1B"
1E"
UJ"
UK"
1M"
1W"
0_"
0b"
1g"
1h"
1k"
Up"
Uq"
#410000000
0#
0(
08
0B
1J
1M
UR
US
0V
1[
1\
0^
0h
1p
1s
Ux
Uy
0|
1$"
1%"
0'"
01"
19"
1<"
UA"
UB"
0E"
1J"
1K"
0M"
0W"
1_"
1b"
Ug"
Uh"
0k"
1p"
1q"
#420000000
1#
1(
18
1B
0J
0M
1R
1S
1V
U[
U\
1^
1h
0p
0s
1x
1y
1|
U$"
U%"
1'"
11"
09"
0<"
1A"
1B"
1E"
UJ"
UK"
1M"
1W"
0_"
0b"
1g"
1h"
1k"
Up"
Uq"
#430000000
0#
0(
08
0B
1J
1M
UR
US
0V
1[
1\
0^
0h
1p
1s
Ux
Uy
0|
1$"
1%"
0'"
01"
19"
1<"
UA"
UB"
0E"
1J"
1K"
0M"
0W"
1_"
1b"
Ug"
Uh"
0k"
1p"
1q"
#440000000
1#
1(
18
1B
0J
0M
1R
1S
1V
U[
U\
1^
1h
0p
0s
1x
1y
1|
U$"
U%"
1'"
11"
09"
0<"
1A"
1B"
1E"
UJ"
UK"
1M"
1W"
0_"
0b"
1g"
1h"
1k"
Up"
Uq"
#450000000
0#
0(
08
0B
1J
1M
UR
US
0V
1[
1\
0^
0h
1p
1s
Ux
Uy
0|
1$"
1%"
0'"
01"
19"
1<"
UA"
UB"
0E"
1J"
1K"
0M"
0W"
1_"
1b"
Ug"
Uh"
0k"
1p"
1q"
#460000000
1#
1(
18
1B
0J
0M
1R
1S
1V
U[
U\
1^
1h
0p
0s
1x
1y
1|
U$"
U%"
1'"
11"
09"
0<"
1A"
1B"
1E"
UJ"
UK"
1M"
1W"
0_"
0b"
1g"
1h"
1k"
Up"
Uq"
#470000000
0#
0(
08
0B
1J
1M
UR
US
0V
1[
1\
0^
0h
1p
1s
Ux
Uy
0|
1$"
1%"
0'"
01"
19"
1<"
UA"
UB"
0E"
1J"
1K"
0M"
0W"
1_"
1b"
Ug"
Uh"
0k"
1p"
1q"
#480000000
1#
1(
18
1B
0J
0M
1R
1S
1V
U[
U\
1^
1h
0p
0s
1x
1y
1|
U$"
U%"
1'"
11"
09"
0<"
1A"
1B"
1E"
UJ"
UK"
1M"
1W"
0_"
0b"
1g"
1h"
1k"
Up"
Uq"
#490000000
0#
0(
08
0B
1J
1M
UR
US
0V
1[
1\
0^
0h
1p
1s
Ux
Uy
0|
1$"
1%"
0'"
01"
19"
1<"
UA"
UB"
0E"
1J"
1K"
0M"
0W"
1_"
1b"
Ug"
Uh"
0k"
1p"
1q"
#500000000
1#
1(
18
1B
0J
0M
1R
1S
1V
U[
U\
1^
1h
0p
0s
1x
1y
1|
U$"
U%"
1'"
11"
09"
0<"
1A"
1B"
1E"
UJ"
UK"
1M"
1W"
0_"
0b"
1g"
1h"
1k"
Up"
Uq"
#510000000
0#
0(
08
0B
1J
1M
UR
US
0V
1[
1\
0^
0h
1p
1s
Ux
Uy
0|
1$"
1%"
0'"
01"
19"
1<"
UA"
UB"
0E"
1J"
1K"
0M"
0W"
1_"
1b"
Ug"
Uh"
0k"
1p"
1q"
#520000000
1#
1(
18
1B
0J
0M
1R
1S
1V
U[
U\
1^
1h
0p
0s
1x
1y
1|
U$"
U%"
1'"
11"
09"
0<"
1A"
1B"
1E"
UJ"
UK"
1M"
1W"
0_"
0b"
1g"
1h"
1k"
Up"
Uq"
#530000000
0#
0(
08
0B
1J
1M
UR
US
0V
1[
1\
0^
0h
1p
1s
Ux
Uy
0|
1$"
1%"
0'"
01"
19"
1<"
UA"
UB"
0E"
1J"
1K"
0M"
0W"
1_"
1b"
Ug"
Uh"
0k"
1p"
1q"
#540000000
1#
1(
18
1B
0J
0M
1R
1S
1V
U[
U\
1^
1h
0p
0s
1x
1y
1|
U$"
U%"
1'"
11"
09"
0<"
1A"
1B"
1E"
UJ"
UK"
1M"
1W"
0_"
0b"
1g"
1h"
1k"
Up"
Uq"
#550000000
0#
0(
08
0B
1J
1M
UR
US
0V
1[
1\
0^
0h
1p
1s
Ux
Uy
0|
1$"
1%"
0'"
01"
19"
1<"
UA"
UB"
0E"
1J"
1K"
0M"
0W"
1_"
1b"
Ug"
Uh"
0k"
1p"
1q"
#560000000
1#
1(
18
1B
0J
0M
1R
1S
1V
U[
U\
1^
1h
0p
0s
1x
1y
1|
U$"
U%"
1'"
11"
09"
0<"
1A"
1B"
1E"
UJ"
UK"
1M"
1W"
0_"
0b"
1g"
1h"
1k"
Up"
Uq"
#570000000
0#
0(
08
0B
1J
1M
UR
US
0V
1[
1\
0^
0h
1p
1s
Ux
Uy
0|
1$"
1%"
0'"
01"
19"
1<"
UA"
UB"
0E"
1J"
1K"
0M"
0W"
1_"
1b"
Ug"
Uh"
0k"
1p"
1q"
#580000000
1#
1(
18
1B
0J
0M
1R
1S
1V
U[
U\
1^
1h
0p
0s
1x
1y
1|
U$"
U%"
1'"
11"
09"
0<"
1A"
1B"
1E"
UJ"
UK"
1M"
1W"
0_"
0b"
1g"
1h"
1k"
Up"
Uq"
