UART/Lab_3/mux2to1.vhd
LIBRARY ieee;
USE ieee.std_logic_1164.ALL;

entity mux2to1 is
	port(
	
		sel : in std_logic;
		a : in std_logic;
        b : in std_logic;
		output : out std_logic
	
	);
end entity mux2to1;

architecture rtl of mux2to1 is

    signal aAnd, bAnd : std_logic;

	begin
	
		aAnd <= a and not sel;
        bAnd <= b and sel;
        
        output <= aAnd or bAnd;
		
end architecture rtl;

UART/Lab_3/mux2to1tb.vhd
LIBRARY ieee;
USE ieee.std_logic_1164.ALL;

entity mux2to1tb is
end entity mux2to1tb;

architecture rtl of mux2to1tb is

    component mux2to1 is

        port(
	
            sel : in std_logic;
            a : in std_logic;
            b : in std_logic;
            output : out std_logic
	
	    );

    end component mux2to1;

    signal selector, a, b, output : std_logic;

	begin
	
		mux2to1Comp: mux2to1 port map (

            sel => selector,
            a => a,
            b => b,
            output => output

        );

        testbench : process

            begin

                selector <= '0';
                a <= '0';
                b <= '0';
                wait for 20 ns;
                assert( (output = '0') )
                report "test failed for combination S=0, a=0, b=0" severity error;

                selector <= '0';
                a <= '1';
                b <= '0';
                wait for 20 ns;
                assert( (output = '1') )
                report "test failed for combination S=0, a=1, b=0" severity error;

                selector <= '0';
                a <= '0';
                b <= '1';
                wait for 20 ns;
                assert( (output = '0') )
                report "test failed for combination S=0, a=0, b=1" severity error;

                selector <= '0';
                a <= '1';
                b <= '1';
                wait for 20 ns;
                assert( (output = '1') )
                report "test failed for combination S=0, a=1, b=1" severity error;

                selector <= '1';
                a <= '0';
                b <= '0';
                wait for 20 ns;
                assert( (output = '0') )
                report "test failed for combination S=1, a=0, b=0" severity error;

                selector <= '1';
                a <= '1';
                b <= '0';
                wait for 20 ns;
                assert( (output = '0') )
                report "test failed for combination S=1, a=1, b=0" severity error;

                selector <= '1';
                a <= '0';
                b <= '1';
                wait for 20 ns;
                assert( (output = '1') )
                report "test failed for combination S=1, a=0, b=1" severity error;

                selector <= '1';
                a <= '1';
                b <= '1';
                wait for 20 ns;
                assert( (output = '1') )
                report "test failed for combination S=1, a=1, b=1" severity error;

                wait;

        end process;
		
end architecture rtl;

UART/Lab_3/mux2to1.vcd
$date
  Mon Nov 07 00:09:39 2022
$end
$version
  GHDL v0
$end
$timescale
  1 fs
$end
$scope module standard $end
$upscope $end
$scope module std_logic_1164 $end
$upscope $end
$scope module mux2to1tb $end
$var reg 1 ! selector $end
$var reg 1 " a $end
$var reg 1 # b $end
$var reg 1 $ output $end
$scope module mux2to1comp $end
$var reg 1 % sel $end
$var reg 1 & a $end
$var reg 1 ' b $end
$var reg 1 ( output $end
$var reg 1 ) aand $end
$var reg 1 * band $end
$upscope $end
$upscope $end
$enddefinitions $end
#0
0!
0"
0#
0$
0%
0&
0'
0(
0)
0*
#20000000
1"
1$
1&
1(
1)
#40000000
0"
1#
0$
0&
1'
0(
0)
#60000000
1"
1$
1&
1(
1)
#80000000
1!
0"
0#
0$
1%
0&
0'
0(
0)
#100000000
1"
1&
#120000000
0"
1#
1$
0&
1'
1(
1*
#140000000
1"
1&
