UART/Lab_3/nor_gate.vhd
LIBRARY ieee;
USE ieee.std_logic_1164.ALL;

entity nor_gate is
	port(

			x_nor : in std_logic;
			y_nor : in std_logic;

			z_nor : out std_logic

		);
end entity nor_gate;


architecture rtl of nor_gate is

	begin
	
		z_nor <= x_nor nor y_nor;
		
end architecture rtl;

UART/Lab_3/srFlipFlop.vhd
LIBRARY ieee;
USE ieee.std_logic_1164.ALL;

entity srFlipFlop is
	port(
	
		set, reset : in std_logic;
		q, qBar : out std_logic
	
	);
end srFlipFlop;

architecture rtl of srFlipFlop is

	component nor_gate is

		port(

			x_nor : in std_logic;
			y_nor : in std_logic;

			z_nor : out std_logic

		);
	
	end component nor_gate;

	signal int_q, int_qBar : std_logic;

	begin

		sNor: nor_gate port map (
			x_nor => set,
            y_nor => int_qBar,

            z_nor => int_q
		);

		rNor: nor_gate port map (
			x_nor => reset,
            y_nor => int_q,

            z_nor => int_qBar
		);

		q <= int_q;
		qBar <= int_qBar;

end architecture rtl;

UART/Lab_3/and3_gate.vhd
LIBRARY ieee;
USE ieee.std_logic_1164.ALL;

entity and3_gate is
	port(

			x_and : in std_logic;
			y_and : in std_logic;
            z_and : in std_logic;

			out_and : out std_logic

		);
end entity and3_gate;


architecture rtl of and3_gate is

	begin
	
		out_and <= x_and and y_and and z_and;
		
end architecture rtl;

UART/Lab_3/tFlipFlop.vhd
LIBRARY ieee;
USE ieee.std_logic_1164.ALL;

entity tFlipFlop is
	port(
	
		i_t : in std_logic;
		t_clock : in std_logic;
		out_q, out_qBar : out std_logic

	);
end entity tFlipFlop;

architecture rtl of tFlipFlop is

    component xor_gate is

        port (
            x_xor : in std_logic;
            y_xor : in std_logic;

            z_xor : out std_logic
        );

    end component xor_gate;

    component nor_gate is 

        port(

            x_nor : in std_logic;
            y_nor : in std_logic;

            z_nor : out std_logic

        );

    end component nor_gate;

    component and3_gate is 

        port(

            x_and : in std_logic;
            y_and : in std_logic;
            z_and : in std_logic;

            out_and : out std_logic

        );

    end component and3_gate;

    component srFlipFlop is

        port(
	
            set, reset : in std_logic;
            q, qBar : out std_logic
        
        );

    end component srFlipFlop;

    
        signal rNorSignal, sNorSignal, qSignal, qBarSignal : std_logic;

    begin

        rAndGate: and3_gate port map (
                x_and => i_t,
                y_and => t_clock,
                z_and => qSignal,

                out_and => rNorSignal

		);

        sAndGate: and3_gate port map (
                x_and => i_t,
                y_and => t_clock,
                z_and => qBarSignal,

                out_and => sNorSignal

		);

        flipflopSR: srFLipFlop port map (

            set => rNorSignal,
            reset => sNorsignal,
		    q => qSignal,
            qBar => qBarSignal

        );
        
        out_q <= qSignal;
        out_qBar <= qBarSignal;

end rtl;

UART/Lab_3/tFlipFloptb.vhd
LIBRARY ieee;
USE ieee.std_logic_1164.ALL;

entity tFlipFloptb is
end entity tFlipFloptb;

architecture rtl of tFlipFloptb is

    component tFlipFlop is

        port(
	
            i_t : in std_logic;
            t_clock : in std_logic;
            out_q, out_qBar : out std_logic

    	);
    
    end component tFlipFlop;
    
    constant T : time := 20 ns;
    signal t_clock, q, qBar, i_t : std_logic := '0';

    begin

        flipFlop : tFlipFlop port map (
            i_t => i_t,
            t_clock => t_clock,

            out_q => q,
            out_qBar => qBar
        );

        clock : process

            begin

                t_clock <= '1';
                wait for T/2;

                t_clock <= '0';
                wait for T/2;


        end process;

        testbench: process

            begin

                i_t <= '0';
                wait for 20 ns;
                assert( (q='0') and (qBar='1') )
                report "Test failed for T=0 with Q(t)=0" severity error;

                i_t <= '1';
                wait for 20 ns;
                assert( (q='1') and (qBar='0') )
                report "Test failed for T=1 with Q'(t)=1" severity error;

        end process;
        

end rtl ; -- tFlipFloptb

UART/Lab_3/TFlipFlopTb.vcd
$date
  Sun Nov 06 14:20:40 2022
$end
$version
  GHDL v0
$end
$timescale
  1 fs
$end
$scope module standard $end
$upscope $end
$scope module std_logic_1164 $end
$upscope $end
$scope module tflipfloptb $end
$var reg 1 ! t_clock $end
$var reg 1 " q $end
$var reg 1 # qbar $end
$var reg 1 $ i_t $end
$scope module flipflop $end
$var reg 1 % i_t $end
$var reg 1 & t_clock $end
$var reg 1 ' out_q $end
$var reg 1 ( out_qbar $end
$var reg 1 ) rnorsignal $end
$var reg 1 * snorsignal $end
$var reg 1 + qsignal $end
$var reg 1 , qbarsignal $end
$scope module randgate $end
$var reg 1 - x_and $end
$var reg 1 . y_and $end
$var reg 1 / z_and $end
$var reg 1 0 out_and $end
$upscope $end
$scope module sandgate $end
$var reg 1 1 x_and $end
$var reg 1 2 y_and $end
$var reg 1 3 z_and $end
$var reg 1 4 out_and $end
$upscope $end
$scope module flipflopsr $end
$var reg 1 5 set $end
$var reg 1 6 reset $end
$var reg 1 7 q $end
$var reg 1 8 qbar $end
$var reg 1 9 int_q $end
$var reg 1 : int_qbar $end
$scope module snor $end
$var reg 1 ; x_nor $end
$var reg 1 < y_nor $end
$var reg 1 = z_nor $end
$upscope $end
$scope module rnor $end
$var reg 1 > x_nor $end
$var reg 1 ? y_nor $end
$var reg 1 @ z_nor $end
$upscope $end
$upscope $end
$upscope $end
$upscope $end
$enddefinitions $end
#0
1!
U"
U#
0$
0%
1&
U'
U(
0)
0*
U+
U,
0-
1.
U/
00
01
12
U3
04
05
06
U7
U8
U9
U:
0;
U<
U=
0>
U?
U@
#10000000
0!
0&
0.
02
#20000000
1!
1$
1%
1&
U)
U*
1-
1.
U0
11
12
U4
U5
U6
U;
U>
#30000000
0!
0&
0)
0*
0.
00
02
04
05
06
0;
0>
#40000000
1!
0$
0%
1&
0-
1.
01
12
#50000000
0!
0&
0.
02
#60000000
1!
1$
1%
1&
U)
U*
1-
1.
U0
11
12
U4
U5
U6
U;
U>
#70000000
0!
0&
0)
0*
0.
00
02
04
05
06
0;
0>
#80000000
1!
0$
0%
1&
0-
1.
01
12
#90000000
0!
0&
0.
02
#100000000
1!
1$
1%
1&
U)
U*
1-
1.
U0
11
12
U4
U5
U6
U;
U>
